{
    "elements": [
        [
            1,
            [
                {
                    "state": {
                        "x": 9,
                        "y": 20,
                        "heading": "NW"
                    },
                    "depth": 1,
                    "horizon": 60,
                    "prev": null
                },
                {
                    "state": {
                        "x": 11,
                        "y": 18,
                        "heading": "W"
                    },
                    "depth": 2,
                    "horizon": 60,
                    "prev": null
                },
                {
                    "state": {
                        "x": 13,
                        "y": 16,
                        "heading": "SW"
                    },
                    "depth": 3,
                    "horizon": 60,
                    "prev": null
                },
                {
                    "state": {
                        "x": 14,
                        "y": 15,
                        "heading": "SW"
                    },
                    "depth": 4,
                    "horizon": 60,
                    "prev": null
                },
                {
                    "state": {
                        "x": 16,
                        "y": 13,
                        "heading": "SW"
                    },
                    "depth": 5,
                    "horizon": 60,
                    "prev": null
                },
                {
                    "state": {
                        "x": 18,
                        "y": 11,
                        "heading": "W"
                    },
                    "depth": 6,
                    "horizon": 60,
                    "prev": null
                },
                {
                    "state": {
                        "x": 18,
                        "y": 9,
                        "heading": "W"
                    },
                    "depth": 7,
                    "horizon": 60,
                    "prev": null
                },
                {
                    "state": {
                        "x": 18,
                        "y": 9,
                        "heading": "W"
                    },
                    "depth": 8,
                    "horizon": 60,
                    "prev": null
                },
                {
                    "state": {
                        "x": 18,
                        "y": 9,
                        "heading": "W"
                    },
                    "depth": 9,
                    "horizon": 60,
                    "prev": null
                },
                {
                    "state": {
                        "x": 18,
                        "y": 9,
                        "heading": "W"
                    },
                    "depth": 10,
                    "horizon": 60,
                    "prev": null
                },
                {
                    "state": {
                        "x": 18,
                        "y": 9,
                        "heading": "W"
                    },
                    "depth": 11,
                    "horizon": 60,
                    "prev": null
                },
                {
                    "state": {
                        "x": 18,
                        "y": 9,
                        "heading": "W"
                    },
                    "depth": 12,
                    "horizon": 60,
                    "prev": null
                },
                {
                    "state": {
                        "x": 18,
                        "y": 9,
                        "heading": "W"
                    },
                    "depth": 13,
                    "horizon": 60,
                    "prev": null
                },
                {
                    "state": {
                        "x": 18,
                        "y": 9,
                        "heading": "W"
                    },
                    "depth": 14,
                    "horizon": 60,
                    "prev": null
                },
                {
                    "state": {
                        "x": 18,
                        "y": 9,
                        "heading": "W"
                    },
                    "depth": 15,
                    "horizon": 60,
                    "prev": null
                },
                {
                    "state": {
                        "x": 18,
                        "y": 9,
                        "heading": "W"
                    },
                    "depth": 16,
                    "horizon": 60,
                    "prev": null
                },
                {
                    "state": {
                        "x": 18,
                        "y": 9,
                        "heading": "W"
                    },
                    "depth": 17,
                    "horizon": 60,
                    "prev": null
                },
                {
                    "state": {
                        "x": 18,
                        "y": 9,
                        "heading": "W"
                    },
                    "depth": 18,
                    "horizon": 60,
                    "prev": null
                },
                {
                    "state": {
                        "x": 18,
                        "y": 9,
                        "heading": "W"
                    },
                    "depth": 19,
                    "horizon": 60,
                    "prev": null
                },
                {
                    "state": {
                        "x": 18,
                        "y": 9,
                        "heading": "W"
                    },
                    "depth": 20,
                    "horizon": 60,
                    "prev": null
                },
                {
                    "state": {
                        "x": 18,
                        "y": 9,
                        "heading": "W"
                    },
                    "depth": 21,
                    "horizon": 60,
                    "prev": null
                },
                {
                    "state": {
                        "x": 18,
                        "y": 9,
                        "heading": "W"
                    },
                    "depth": 22,
                    "horizon": 60,
                    "prev": null
                },
                {
                    "state": {
                        "x": 18,
                        "y": 9,
                        "heading": "W"
                    },
                    "depth": 23,
                    "horizon": 60,
                    "prev": null
                },
                {
                    "state": {
                        "x": 18,
                        "y": 9,
                        "heading": "W"
                    },
                    "depth": 24,
                    "horizon": 60,
                    "prev": null
                },
                {
                    "state": {
                        "x": 18,
                        "y": 9,
                        "heading": "W"
                    },
                    "depth": 25,
                    "horizon": 60,
                    "prev": null
                },
                {
                    "state": {
                        "x": 18,
                        "y": 9,
                        "heading": "W"
                    },
                    "depth": 26,
                    "horizon": 60,
                    "prev": null
                },
                {
                    "state": {
                        "x": 18,
                        "y": 9,
                        "heading": "W"
                    },
                    "depth": 27,
                    "horizon": 60,
                    "prev": null
                },
                {
                    "state": {
                        "x": 18,
                        "y": 9,
                        "heading": "W"
                    },
                    "depth": 28,
                    "horizon": 60,
                    "prev": null
                },
                {
                    "state": {
                        "x": 18,
                        "y": 9,
                        "heading": "W"
                    },
                    "depth": 29,
                    "horizon": 60,
                    "prev": null
                },
                {
                    "state": {
                        "x": 18,
                        "y": 9,
                        "heading": "W"
                    },
                    "depth": 30,
                    "horizon": 60,
                    "prev": null
                },
                {
                    "state": {
                        "x": 18,
                        "y": 9,
                        "heading": "W"
                    },
                    "depth": 31,
                    "horizon": 60,
                    "prev": null
                },
                {
                    "state": {
                        "x": 18,
                        "y": 9,
                        "heading": "W"
                    },
                    "depth": 32,
                    "horizon": 60,
                    "prev": null
                },
                {
                    "state": {
                        "x": 18,
                        "y": 9,
                        "heading": "W"
                    },
                    "depth": 33,
                    "horizon": 60,
                    "prev": null
                },
                {
                    "state": {
                        "x": 18,
                        "y": 9,
                        "heading": "W"
                    },
                    "depth": 34,
                    "horizon": 60,
                    "prev": null
                },
                {
                    "state": {
                        "x": 18,
                        "y": 9,
                        "heading": "W"
                    },
                    "depth": 35,
                    "horizon": 60,
                    "prev": null
                },
                {
                    "state": {
                        "x": 18,
                        "y": 9,
                        "heading": "W"
                    },
                    "depth": 36,
                    "horizon": 60,
                    "prev": null
                },
                {
                    "state": {
                        "x": 18,
                        "y": 9,
                        "heading": "W"
                    },
                    "depth": 37,
                    "horizon": 60,
                    "prev": null
                },
                {
                    "state": {
                        "x": 18,
                        "y": 9,
                        "heading": "W"
                    },
                    "depth": 38,
                    "horizon": 60,
                    "prev": null
                },
                {
                    "state": {
                        "x": 18,
                        "y": 9,
                        "heading": "W"
                    },
                    "depth": 39,
                    "horizon": 60,
                    "prev": null
                },
                {
                    "state": {
                        "x": 18,
                        "y": 9,
                        "heading": "W"
                    },
                    "depth": 40,
                    "horizon": 60,
                    "prev": null
                },
                {
                    "state": {
                        "x": 18,
                        "y": 9,
                        "heading": "W"
                    },
                    "depth": 41,
                    "horizon": 60,
                    "prev": null
                },
                {
                    "state": {
                        "x": 18,
                        "y": 9,
                        "heading": "W"
                    },
                    "depth": 42,
                    "horizon": 60,
                    "prev": null
                },
                {
                    "state": {
                        "x": 18,
                        "y": 9,
                        "heading": "W"
                    },
                    "depth": 43,
                    "horizon": 60,
                    "prev": null
                },
                {
                    "state": {
                        "x": 18,
                        "y": 9,
                        "heading": "W"
                    },
                    "depth": 44,
                    "horizon": 60,
                    "prev": null
                },
                {
                    "state": {
                        "x": 18,
                        "y": 9,
                        "heading": "W"
                    },
                    "depth": 45,
                    "horizon": 60,
                    "prev": null
                },
                {
                    "state": {
                        "x": 18,
                        "y": 9,
                        "heading": "W"
                    },
                    "depth": 46,
                    "horizon": 60,
                    "prev": null
                },
                {
                    "state": {
                        "x": 18,
                        "y": 9,
                        "heading": "W"
                    },
                    "depth": 47,
                    "horizon": 60,
                    "prev": null
                },
                {
                    "state": {
                        "x": 18,
                        "y": 9,
                        "heading": "W"
                    },
                    "depth": 48,
                    "horizon": 60,
                    "prev": null
                },
                {
                    "state": {
                        "x": 18,
                        "y": 9,
                        "heading": "W"
                    },
                    "depth": 49,
                    "horizon": 60,
                    "prev": null
                },
                {
                    "state": {
                        "x": 18,
                        "y": 9,
                        "heading": "W"
                    },
                    "depth": 50,
                    "horizon": 60,
                    "prev": null
                },
                {
                    "state": {
                        "x": 18,
                        "y": 9,
                        "heading": "W"
                    },
                    "depth": 51,
                    "horizon": 60,
                    "prev": null
                },
                {
                    "state": {
                        "x": 18,
                        "y": 9,
                        "heading": "W"
                    },
                    "depth": 52,
                    "horizon": 60,
                    "prev": null
                },
                {
                    "state": {
                        "x": 18,
                        "y": 9,
                        "heading": "W"
                    },
                    "depth": 53,
                    "horizon": 60,
                    "prev": null
                },
                {
                    "state": {
                        "x": 18,
                        "y": 9,
                        "heading": "W"
                    },
                    "depth": 54,
                    "horizon": 60,
                    "prev": null
                },
                {
                    "state": {
                        "x": 18,
                        "y": 9,
                        "heading": "W"
                    },
                    "depth": 55,
                    "horizon": 60,
                    "prev": null
                },
                {
                    "state": {
                        "x": 18,
                        "y": 9,
                        "heading": "W"
                    },
                    "depth": 56,
                    "horizon": 60,
                    "prev": null
                },
                {
                    "state": {
                        "x": 18,
                        "y": 9,
                        "heading": "W"
                    },
                    "depth": 57,
                    "horizon": 60,
                    "prev": null
                },
                {
                    "state": {
                        "x": 18,
                        "y": 9,
                        "heading": "W"
                    },
                    "depth": 58,
                    "horizon": 60,
                    "prev": null
                },
                {
                    "state": {
                        "x": 18,
                        "y": 9,
                        "heading": "W"
                    },
                    "depth": 59,
                    "horizon": 60,
                    "prev": null
                },
                {
                    "state": {
                        "x": 18,
                        "y": 9,
                        "heading": "W"
                    },
                    "depth": 60,
                    "horizon": 60,
                    "prev": null
                }
            ]
        ],
        [
            2,
            [
                {
                    "state": {
                        "x": 11,
                        "y": 17,
                        "heading": "SW"
                    },
                    "depth": 1,
                    "horizon": 60,
                    "prev": null
                },
                {
                    "state": {
                        "x": 9,
                        "y": 17,
                        "heading": "S"
                    },
                    "depth": 2,
                    "horizon": 60,
                    "prev": null
                },
                {
                    "state": {
                        "x": 7,
                        "y": 15,
                        "heading": "S"
                    },
                    "depth": 3,
                    "horizon": 60,
                    "prev": null
                },
                {
                    "state": {
                        "x": 5,
                        "y": 13,
                        "heading": "SE"
                    },
                    "depth": 4,
                    "horizon": 60,
                    "prev": null
                },
                {
                    "state": {
                        "x": 3,
                        "y": 11,
                        "heading": "E"
                    },
                    "depth": 5,
                    "horizon": 60,
                    "prev": null
                },
                {
                    "state": {
                        "x": 1,
                        "y": 9,
                        "heading": "E"
                    },
                    "depth": 6,
                    "horizon": 60,
                    "prev": null
                },
                {
                    "state": {
                        "x": 1,
                        "y": 9,
                        "heading": "E"
                    },
                    "depth": 7,
                    "horizon": 60,
                    "prev": null
                },
                {
                    "state": {
                        "x": 1,
                        "y": 9,
                        "heading": "E"
                    },
                    "depth": 8,
                    "horizon": 60,
                    "prev": null
                },
                {
                    "state": {
                        "x": 1,
                        "y": 9,
                        "heading": "E"
                    },
                    "depth": 9,
                    "horizon": 60,
                    "prev": null
                },
                {
                    "state": {
                        "x": 1,
                        "y": 9,
                        "heading": "E"
                    },
                    "depth": 10,
                    "horizon": 60,
                    "prev": null
                },
                {
                    "state": {
                        "x": 1,
                        "y": 9,
                        "heading": "E"
                    },
                    "depth": 11,
                    "horizon": 60,
                    "prev": null
                },
                {
                    "state": {
                        "x": 1,
                        "y": 9,
                        "heading": "E"
                    },
                    "depth": 12,
                    "horizon": 60,
                    "prev": null
                },
                {
                    "state": {
                        "x": 1,
                        "y": 9,
                        "heading": "E"
                    },
                    "depth": 13,
                    "horizon": 60,
                    "prev": null
                },
                {
                    "state": {
                        "x": 1,
                        "y": 9,
                        "heading": "E"
                    },
                    "depth": 14,
                    "horizon": 60,
                    "prev": null
                },
                {
                    "state": {
                        "x": 1,
                        "y": 9,
                        "heading": "E"
                    },
                    "depth": 15,
                    "horizon": 60,
                    "prev": null
                },
                {
                    "state": {
                        "x": 1,
                        "y": 9,
                        "heading": "E"
                    },
                    "depth": 16,
                    "horizon": 60,
                    "prev": null
                },
                {
                    "state": {
                        "x": 1,
                        "y": 9,
                        "heading": "E"
                    },
                    "depth": 17,
                    "horizon": 60,
                    "prev": null
                },
                {
                    "state": {
                        "x": 1,
                        "y": 9,
                        "heading": "E"
                    },
                    "depth": 18,
                    "horizon": 60,
                    "prev": null
                },
                {
                    "state": {
                        "x": 1,
                        "y": 9,
                        "heading": "E"
                    },
                    "depth": 19,
                    "horizon": 60,
                    "prev": null
                },
                {
                    "state": {
                        "x": 1,
                        "y": 9,
                        "heading": "E"
                    },
                    "depth": 20,
                    "horizon": 60,
                    "prev": null
                },
                {
                    "state": {
                        "x": 1,
                        "y": 9,
                        "heading": "E"
                    },
                    "depth": 21,
                    "horizon": 60,
                    "prev": null
                },
                {
                    "state": {
                        "x": 1,
                        "y": 9,
                        "heading": "E"
                    },
                    "depth": 22,
                    "horizon": 60,
                    "prev": null
                },
                {
                    "state": {
                        "x": 1,
                        "y": 9,
                        "heading": "E"
                    },
                    "depth": 23,
                    "horizon": 60,
                    "prev": null
                },
                {
                    "state": {
                        "x": 1,
                        "y": 9,
                        "heading": "E"
                    },
                    "depth": 24,
                    "horizon": 60,
                    "prev": null
                },
                {
                    "state": {
                        "x": 1,
                        "y": 9,
                        "heading": "E"
                    },
                    "depth": 25,
                    "horizon": 60,
                    "prev": null
                },
                {
                    "state": {
                        "x": 1,
                        "y": 9,
                        "heading": "E"
                    },
                    "depth": 26,
                    "horizon": 60,
                    "prev": null
                },
                {
                    "state": {
                        "x": 1,
                        "y": 9,
                        "heading": "E"
                    },
                    "depth": 27,
                    "horizon": 60,
                    "prev": null
                },
                {
                    "state": {
                        "x": 1,
                        "y": 9,
                        "heading": "E"
                    },
                    "depth": 28,
                    "horizon": 60,
                    "prev": null
                },
                {
                    "state": {
                        "x": 1,
                        "y": 9,
                        "heading": "E"
                    },
                    "depth": 29,
                    "horizon": 60,
                    "prev": null
                },
                {
                    "state": {
                        "x": 1,
                        "y": 9,
                        "heading": "E"
                    },
                    "depth": 30,
                    "horizon": 60,
                    "prev": null
                },
                {
                    "state": {
                        "x": 1,
                        "y": 9,
                        "heading": "E"
                    },
                    "depth": 31,
                    "horizon": 60,
                    "prev": null
                },
                {
                    "state": {
                        "x": 1,
                        "y": 9,
                        "heading": "E"
                    },
                    "depth": 32,
                    "horizon": 60,
                    "prev": null
                },
                {
                    "state": {
                        "x": 1,
                        "y": 9,
                        "heading": "E"
                    },
                    "depth": 33,
                    "horizon": 60,
                    "prev": null
                },
                {
                    "state": {
                        "x": 1,
                        "y": 9,
                        "heading": "E"
                    },
                    "depth": 34,
                    "horizon": 60,
                    "prev": null
                },
                {
                    "state": {
                        "x": 1,
                        "y": 9,
                        "heading": "E"
                    },
                    "depth": 35,
                    "horizon": 60,
                    "prev": null
                },
                {
                    "state": {
                        "x": 1,
                        "y": 9,
                        "heading": "E"
                    },
                    "depth": 36,
                    "horizon": 60,
                    "prev": null
                },
                {
                    "state": {
                        "x": 1,
                        "y": 9,
                        "heading": "E"
                    },
                    "depth": 37,
                    "horizon": 60,
                    "prev": null
                },
                {
                    "state": {
                        "x": 1,
                        "y": 9,
                        "heading": "E"
                    },
                    "depth": 38,
                    "horizon": 60,
                    "prev": null
                },
                {
                    "state": {
                        "x": 1,
                        "y": 9,
                        "heading": "E"
                    },
                    "depth": 39,
                    "horizon": 60,
                    "prev": null
                },
                {
                    "state": {
                        "x": 1,
                        "y": 9,
                        "heading": "E"
                    },
                    "depth": 40,
                    "horizon": 60,
                    "prev": null
                },
                {
                    "state": {
                        "x": 1,
                        "y": 9,
                        "heading": "E"
                    },
                    "depth": 41,
                    "horizon": 60,
                    "prev": null
                },
                {
                    "state": {
                        "x": 1,
                        "y": 9,
                        "heading": "E"
                    },
                    "depth": 42,
                    "horizon": 60,
                    "prev": null
                },
                {
                    "state": {
                        "x": 1,
                        "y": 9,
                        "heading": "E"
                    },
                    "depth": 43,
                    "horizon": 60,
                    "prev": null
                },
                {
                    "state": {
                        "x": 1,
                        "y": 9,
                        "heading": "E"
                    },
                    "depth": 44,
                    "horizon": 60,
                    "prev": null
                },
                {
                    "state": {
                        "x": 1,
                        "y": 9,
                        "heading": "E"
                    },
                    "depth": 45,
                    "horizon": 60,
                    "prev": null
                },
                {
                    "state": {
                        "x": 1,
                        "y": 9,
                        "heading": "E"
                    },
                    "depth": 46,
                    "horizon": 60,
                    "prev": null
                },
                {
                    "state": {
                        "x": 1,
                        "y": 9,
                        "heading": "E"
                    },
                    "depth": 47,
                    "horizon": 60,
                    "prev": null
                },
                {
                    "state": {
                        "x": 1,
                        "y": 9,
                        "heading": "E"
                    },
                    "depth": 48,
                    "horizon": 60,
                    "prev": null
                },
                {
                    "state": {
                        "x": 1,
                        "y": 9,
                        "heading": "E"
                    },
                    "depth": 49,
                    "horizon": 60,
                    "prev": null
                },
                {
                    "state": {
                        "x": 1,
                        "y": 9,
                        "heading": "E"
                    },
                    "depth": 50,
                    "horizon": 60,
                    "prev": null
                },
                {
                    "state": {
                        "x": 1,
                        "y": 9,
                        "heading": "E"
                    },
                    "depth": 51,
                    "horizon": 60,
                    "prev": null
                },
                {
                    "state": {
                        "x": 1,
                        "y": 9,
                        "heading": "E"
                    },
                    "depth": 52,
                    "horizon": 60,
                    "prev": null
                },
                {
                    "state": {
                        "x": 1,
                        "y": 9,
                        "heading": "E"
                    },
                    "depth": 53,
                    "horizon": 60,
                    "prev": null
                },
                {
                    "state": {
                        "x": 1,
                        "y": 9,
                        "heading": "E"
                    },
                    "depth": 54,
                    "horizon": 60,
                    "prev": null
                },
                {
                    "state": {
                        "x": 1,
                        "y": 9,
                        "heading": "E"
                    },
                    "depth": 55,
                    "horizon": 60,
                    "prev": null
                },
                {
                    "state": {
                        "x": 1,
                        "y": 9,
                        "heading": "E"
                    },
                    "depth": 56,
                    "horizon": 60,
                    "prev": null
                },
                {
                    "state": {
                        "x": 1,
                        "y": 9,
                        "heading": "E"
                    },
                    "depth": 57,
                    "horizon": 60,
                    "prev": null
                },
                {
                    "state": {
                        "x": 1,
                        "y": 9,
                        "heading": "E"
                    },
                    "depth": 58,
                    "horizon": 60,
                    "prev": null
                },
                {
                    "state": {
                        "x": 1,
                        "y": 9,
                        "heading": "E"
                    },
                    "depth": 59,
                    "horizon": 60,
                    "prev": null
                },
                {
                    "state": {
                        "x": 1,
                        "y": 9,
                        "heading": "E"
                    },
                    "depth": 60,
                    "horizon": 60,
                    "prev": null
                }
            ]
        ],
        [
            3,
            [
                {
                    "state": {
                        "x": 3,
                        "y": 9,
                        "heading": "SE"
                    },
                    "depth": 1,
                    "horizon": 60,
                    "prev": null
                },
                {
                    "state": {
                        "x": 2,
                        "y": 7,
                        "heading": "E"
                    },
                    "depth": 2,
                    "horizon": 60,
                    "prev": null
                },
                {
                    "state": {
                        "x": 4,
                        "y": 5,
                        "heading": "NE"
                    },
                    "depth": 3,
                    "horizon": 60,
                    "prev": null
                },
                {
                    "state": {
                        "x": 5,
                        "y": 3,
                        "heading": "NE"
                    },
                    "depth": 4,
                    "horizon": 60,
                    "prev": null
                },
                {
                    "state": {
                        "x": 7,
                        "y": 1,
                        "heading": "N"
                    },
                    "depth": 5,
                    "horizon": 60,
                    "prev": null
                },
                {
                    "state": {
                        "x": 7,
                        "y": 1,
                        "heading": "N"
                    },
                    "depth": 6,
                    "horizon": 60,
                    "prev": null
                },
                {
                    "state": {
                        "x": 5,
                        "y": 2,
                        "heading": "NE"
                    },
                    "depth": 7,
                    "horizon": 60,
                    "prev": null
                },
                {
                    "state": {
                        "x": 5,
                        "y": 2,
                        "heading": "NE"
                    },
                    "depth": 8,
                    "horizon": 60,
                    "prev": null
                },
                {
                    "state": {
                        "x": 5,
                        "y": 2,
                        "heading": "NE"
                    },
                    "depth": 9,
                    "horizon": 60,
                    "prev": null
                },
                {
                    "state": {
                        "x": 5,
                        "y": 2,
                        "heading": "NE"
                    },
                    "depth": 10,
                    "horizon": 60,
                    "prev": null
                },
                {
                    "state": {
                        "x": 5,
                        "y": 2,
                        "heading": "NE"
                    },
                    "depth": 11,
                    "horizon": 60,
                    "prev": null
                },
                {
                    "state": {
                        "x": 5,
                        "y": 2,
                        "heading": "NE"
                    },
                    "depth": 12,
                    "horizon": 60,
                    "prev": null
                },
                {
                    "state": {
                        "x": 5,
                        "y": 2,
                        "heading": "NE"
                    },
                    "depth": 13,
                    "horizon": 60,
                    "prev": null
                },
                {
                    "state": {
                        "x": 5,
                        "y": 2,
                        "heading": "NE"
                    },
                    "depth": 14,
                    "horizon": 60,
                    "prev": null
                },
                {
                    "state": {
                        "x": 5,
                        "y": 2,
                        "heading": "NE"
                    },
                    "depth": 15,
                    "horizon": 60,
                    "prev": null
                },
                {
                    "state": {
                        "x": 5,
                        "y": 2,
                        "heading": "NE"
                    },
                    "depth": 16,
                    "horizon": 60,
                    "prev": null
                },
                {
                    "state": {
                        "x": 5,
                        "y": 2,
                        "heading": "NE"
                    },
                    "depth": 17,
                    "horizon": 60,
                    "prev": null
                },
                {
                    "state": {
                        "x": 5,
                        "y": 2,
                        "heading": "NE"
                    },
                    "depth": 18,
                    "horizon": 60,
                    "prev": null
                },
                {
                    "state": {
                        "x": 5,
                        "y": 2,
                        "heading": "NE"
                    },
                    "depth": 19,
                    "horizon": 60,
                    "prev": null
                },
                {
                    "state": {
                        "x": 5,
                        "y": 2,
                        "heading": "NE"
                    },
                    "depth": 20,
                    "horizon": 60,
                    "prev": null
                },
                {
                    "state": {
                        "x": 5,
                        "y": 2,
                        "heading": "NE"
                    },
                    "depth": 21,
                    "horizon": 60,
                    "prev": null
                },
                {
                    "state": {
                        "x": 5,
                        "y": 2,
                        "heading": "NE"
                    },
                    "depth": 22,
                    "horizon": 60,
                    "prev": null
                },
                {
                    "state": {
                        "x": 5,
                        "y": 2,
                        "heading": "NE"
                    },
                    "depth": 23,
                    "horizon": 60,
                    "prev": null
                },
                {
                    "state": {
                        "x": 5,
                        "y": 2,
                        "heading": "NE"
                    },
                    "depth": 24,
                    "horizon": 60,
                    "prev": null
                },
                {
                    "state": {
                        "x": 5,
                        "y": 2,
                        "heading": "NE"
                    },
                    "depth": 25,
                    "horizon": 60,
                    "prev": null
                },
                {
                    "state": {
                        "x": 5,
                        "y": 2,
                        "heading": "NE"
                    },
                    "depth": 26,
                    "horizon": 60,
                    "prev": null
                },
                {
                    "state": {
                        "x": 5,
                        "y": 2,
                        "heading": "NE"
                    },
                    "depth": 27,
                    "horizon": 60,
                    "prev": null
                },
                {
                    "state": {
                        "x": 5,
                        "y": 2,
                        "heading": "NE"
                    },
                    "depth": 28,
                    "horizon": 60,
                    "prev": null
                },
                {
                    "state": {
                        "x": 5,
                        "y": 2,
                        "heading": "NE"
                    },
                    "depth": 29,
                    "horizon": 60,
                    "prev": null
                },
                {
                    "state": {
                        "x": 5,
                        "y": 2,
                        "heading": "NE"
                    },
                    "depth": 30,
                    "horizon": 60,
                    "prev": null
                },
                {
                    "state": {
                        "x": 5,
                        "y": 2,
                        "heading": "NE"
                    },
                    "depth": 31,
                    "horizon": 60,
                    "prev": null
                },
                {
                    "state": {
                        "x": 5,
                        "y": 2,
                        "heading": "NE"
                    },
                    "depth": 32,
                    "horizon": 60,
                    "prev": null
                },
                {
                    "state": {
                        "x": 5,
                        "y": 2,
                        "heading": "NE"
                    },
                    "depth": 33,
                    "horizon": 60,
                    "prev": null
                },
                {
                    "state": {
                        "x": 5,
                        "y": 2,
                        "heading": "NE"
                    },
                    "depth": 34,
                    "horizon": 60,
                    "prev": null
                },
                {
                    "state": {
                        "x": 5,
                        "y": 2,
                        "heading": "NE"
                    },
                    "depth": 35,
                    "horizon": 60,
                    "prev": null
                },
                {
                    "state": {
                        "x": 5,
                        "y": 2,
                        "heading": "NE"
                    },
                    "depth": 36,
                    "horizon": 60,
                    "prev": null
                },
                {
                    "state": {
                        "x": 5,
                        "y": 2,
                        "heading": "NE"
                    },
                    "depth": 37,
                    "horizon": 60,
                    "prev": null
                },
                {
                    "state": {
                        "x": 5,
                        "y": 2,
                        "heading": "NE"
                    },
                    "depth": 38,
                    "horizon": 60,
                    "prev": null
                },
                {
                    "state": {
                        "x": 5,
                        "y": 2,
                        "heading": "NE"
                    },
                    "depth": 39,
                    "horizon": 60,
                    "prev": null
                },
                {
                    "state": {
                        "x": 5,
                        "y": 2,
                        "heading": "NE"
                    },
                    "depth": 40,
                    "horizon": 60,
                    "prev": null
                },
                {
                    "state": {
                        "x": 5,
                        "y": 2,
                        "heading": "NE"
                    },
                    "depth": 41,
                    "horizon": 60,
                    "prev": null
                },
                {
                    "state": {
                        "x": 5,
                        "y": 2,
                        "heading": "NE"
                    },
                    "depth": 42,
                    "horizon": 60,
                    "prev": null
                },
                {
                    "state": {
                        "x": 5,
                        "y": 2,
                        "heading": "NE"
                    },
                    "depth": 43,
                    "horizon": 60,
                    "prev": null
                },
                {
                    "state": {
                        "x": 5,
                        "y": 2,
                        "heading": "NE"
                    },
                    "depth": 44,
                    "horizon": 60,
                    "prev": null
                },
                {
                    "state": {
                        "x": 5,
                        "y": 2,
                        "heading": "NE"
                    },
                    "depth": 45,
                    "horizon": 60,
                    "prev": null
                },
                {
                    "state": {
                        "x": 5,
                        "y": 2,
                        "heading": "NE"
                    },
                    "depth": 46,
                    "horizon": 60,
                    "prev": null
                },
                {
                    "state": {
                        "x": 5,
                        "y": 2,
                        "heading": "NE"
                    },
                    "depth": 47,
                    "horizon": 60,
                    "prev": null
                },
                {
                    "state": {
                        "x": 5,
                        "y": 2,
                        "heading": "NE"
                    },
                    "depth": 48,
                    "horizon": 60,
                    "prev": null
                },
                {
                    "state": {
                        "x": 5,
                        "y": 2,
                        "heading": "NE"
                    },
                    "depth": 49,
                    "horizon": 60,
                    "prev": null
                },
                {
                    "state": {
                        "x": 5,
                        "y": 2,
                        "heading": "NE"
                    },
                    "depth": 50,
                    "horizon": 60,
                    "prev": null
                },
                {
                    "state": {
                        "x": 5,
                        "y": 2,
                        "heading": "NE"
                    },
                    "depth": 51,
                    "horizon": 60,
                    "prev": null
                },
                {
                    "state": {
                        "x": 5,
                        "y": 2,
                        "heading": "NE"
                    },
                    "depth": 52,
                    "horizon": 60,
                    "prev": null
                },
                {
                    "state": {
                        "x": 5,
                        "y": 2,
                        "heading": "NE"
                    },
                    "depth": 53,
                    "horizon": 60,
                    "prev": null
                },
                {
                    "state": {
                        "x": 5,
                        "y": 2,
                        "heading": "NE"
                    },
                    "depth": 54,
                    "horizon": 60,
                    "prev": null
                },
                {
                    "state": {
                        "x": 5,
                        "y": 2,
                        "heading": "NE"
                    },
                    "depth": 55,
                    "horizon": 60,
                    "prev": null
                },
                {
                    "state": {
                        "x": 5,
                        "y": 2,
                        "heading": "NE"
                    },
                    "depth": 56,
                    "horizon": 60,
                    "prev": null
                },
                {
                    "state": {
                        "x": 5,
                        "y": 2,
                        "heading": "NE"
                    },
                    "depth": 57,
                    "horizon": 60,
                    "prev": null
                },
                {
                    "state": {
                        "x": 5,
                        "y": 2,
                        "heading": "NE"
                    },
                    "depth": 58,
                    "horizon": 60,
                    "prev": null
                },
                {
                    "state": {
                        "x": 5,
                        "y": 2,
                        "heading": "NE"
                    },
                    "depth": 59,
                    "horizon": 60,
                    "prev": null
                },
                {
                    "state": {
                        "x": 5,
                        "y": 2,
                        "heading": "NE"
                    },
                    "depth": 60,
                    "horizon": 60,
                    "prev": null
                }
            ]
        ]
    ],
    "value": 2068.272730031511
}